compliance_suite/__init__.py
compliance_suite/constants.py
compliance_suite/helper.py
compliance_suite/report_runner.py
compliance_suite/report_server.py
compliance_suite/validate_drs_object_response.py
compliance_suite/validate_response.py
compliance_suite/schemas/service_info.json
compliance_suite/schemas/service_type.json
compliance_suite/schemas/v1.2.0/access_method.json
compliance_suite/schemas/v1.2.0/access_url.json
compliance_suite/schemas/v1.2.0/checksum.json
compliance_suite/schemas/v1.2.0/contents_object.json
compliance_suite/schemas/v1.2.0/drs_bundle.json
compliance_suite/schemas/v1.2.0/drs_object.json
compliance_suite/schemas/v1.2.0/error.json
compliance_suite/web/temp_report.json
compliance_suite/web/static/style.css
compliance_suite/web/templates/index.html
drs_compliance_suite-1.0.3.dist-info/LICENSE
drs_compliance_suite-1.0.3.dist-info/METADATA
drs_compliance_suite-1.0.3.dist-info/WHEEL
drs_compliance_suite-1.0.3.dist-info/entry_points.txt
drs_compliance_suite-1.0.3.dist-info/top_level.txt
drs_compliance_suite-1.0.3.dist-info/RECORD
