Metadata-Version: 2.1
Name: drs-compliance-suite
Version: 1.0.3
Summary: A compliance utility reporting system for GA4GH DRS server implementations. Supports GA4GH DRS versions - 1.2.0
Home-page: https://github.com/ga4gh/drs-compliance-suite
Author: Yash Puligundla
Author-email: yasasvini.puligundla@ga4gh.org
License: MIT
Requires-Python: >=3.8
License-File: LICENSE
Requires-Dist: python-json-logger (==2.0.4)
Requires-Dist: structlog (==21.5.0)
Requires-Dist: requests (==2.28.1)
Requires-Dist: Flask (==2.2.0)
Requires-Dist: Flask-HTTPAuth (==4.7.0)
Requires-Dist: pytest (==7.1.2)
Requires-Dist: pytest-cov (==3.0.0)
Requires-Dist: ga4gh-testbed-lib (==0.2.0)
